pyctf/CPersist.py
pyctf/CPersist_tmp.py
pyctf/__init__.py
pyctf/avghc.py
pyctf/classfileFunc.py
pyctf/ctf_meg4.py
pyctf/ctf_res4.py
pyctf/dsopen.py
pyctf/fid.py
pyctf/getHC.py
pyctf/getHM.py
pyctf/getfidrot.py
pyctf/markers.py
pyctf/segments.py
pyctf/util.py
pyctf/addMarker/__init__.py
pyctf/addMarker/addMarker.py
pyctf/addMarker/delMarker.py
pyctf_nihmegcore-1.1.1.dist-info/licenses/LICENSE
pyctf_nihmegcore-1.1.1.dist-info/METADATA
pyctf_nihmegcore-1.1.1.dist-info/WHEEL
pyctf_nihmegcore-1.1.1.dist-info/top_level.txt
pyctf_nihmegcore-1.1.1.dist-info/RECORD
