Metadata-Version: 2.4
Name: pyctf-nihmegcore
Version: 1.1.1
Summary: CTF MEG functions integrated into python
Author-email: Tom Holroyd <holroydt@mail.nih.gov>, Jeff Stout <stoutjd@nih.gov>
License-Expression: GPL-3.0
Classifier: Programming Language :: Python :: 3
Classifier: Operating System :: POSIX
License-File: LICENSE
Requires-Dist: numpy
Dynamic: license-file
